packaging_dists/__init__.py
packaging_dists/_utils.py
packaging_dists-0.4.dist-info/LICENSE
packaging_dists-0.4.dist-info/METADATA
packaging_dists-0.4.dist-info/WHEEL
packaging_dists-0.4.dist-info/top_level.txt
packaging_dists-0.4.dist-info/RECORD
